q2_micom/__init__.py
q2_micom/_build.py
q2_micom/_db.py
q2_micom/_filter.py
q2_micom/_formats_and_types.py
q2_micom/_growth.py
q2_micom/_medium.py
q2_micom/_tradeoff.py
q2_micom/_transform.py
q2_micom/_viz.py
q2_micom/citations.bib
q2_micom/plugin_setup.py
q2_micom/tests/__init__.py
q2_micom/tests/test_build.py
q2_micom/tests/test_db.py
q2_micom/tests/test_filter.py
q2_micom/tests/test_growth.py
q2_micom/tests/test_medium.py
q2_micom/tests/test_tradeoff.py
q2_micom/tests/test_transformers.py
q2_micom/tests/test_viz.py
q2_micom-0.16.0.dist-info/LICENSE
q2_micom-0.16.0.dist-info/METADATA
q2_micom-0.16.0.dist-info/WHEEL
q2_micom-0.16.0.dist-info/entry_points.txt
q2_micom-0.16.0.dist-info/top_level.txt
q2_micom-0.16.0.dist-info/RECORD
