Metadata-Version: 2.1
Name: q2-micom
Version: 0.16.0
Summary: QIIME 2 plugin for metabolic modeling of microbial communities.
Home-page: https://github.com/micom-dev/q2-micom
Author: Christian Diener
Author-email: mail@cdiener.com,
License: Apache License 2.0
Keywords: microbiome,modeling,metabolism,community
Classifier: Development Status :: 4 - Beta
Classifier: Intended Audience :: Science/Research
Classifier: Topic :: Scientific/Engineering :: Bio-Informatics
Classifier: License :: OSI Approved :: Apache Software License
Classifier: Programming Language :: Python :: 3
Classifier: Programming Language :: Python :: 3.8
Classifier: Programming Language :: Python :: 3.9
Classifier: Programming Language :: Python :: 3.10
Classifier: Programming Language :: Python :: 3.11
Requires-Python: >=3.6
License-File: LICENSE
Requires-Dist: cobra>=0.29.0
Requires-Dist: micom>=0.37.0
Requires-Dist: jinja2>=2.10.3
Requires-Dist: qiime2>=2023.2
Requires-Dist: rich>=6.0
Requires-Dist: pandas>=1.0
Requires-Dist: numpy<2.0
